getbuildings/__init__.py
getbuildings/main.py
getbuildings-0.1.1.dist-info/METADATA
getbuildings-0.1.1.dist-info/WHEEL
getbuildings-0.1.1.dist-info/entry_points.txt
getbuildings-0.1.1.dist-info/top_level.txt
getbuildings-0.1.1.dist-info/RECORD
